{
    "realms": {
        "master": {
            "workspaces": {
                "local": [ "local_default" ],
                "dev": [],
                "test": [],
                "prod": []
            }
        },
        "customers": {
            "workspaces": {
                "local": [ "local_default" ],
                "dev": [],
                "test": [],
                "prod": []
            }
        },
        "employees": {
            "workspaces": {
                "local": [ "local_default" ],
                "dev": [],
                "test": [],
                "prod": []
            }
        }
    },
    "environments": {
        "local": {
            "keycloak_url": "http://idp:8080",
            "username": "sherpaciamhome",
            "password": "$env:LOCAL_KEYCLOAK_PASSWORD"
        },
        "dev": {
            "keycloak_url": "https://dev.identicum.com"
        },
        "test": {
            "keycloak_url": "https://test-idp.identicum.com"
        },
        "prod": {
            "keycloak_url": "https://idp.identicum.com"
        }
    }
}